myprograms/__init__.py
myprograms/p1.c
mr_nobody-1.0.1.dist-info/METADATA
mr_nobody-1.0.1.dist-info/WHEEL
mr_nobody-1.0.1.dist-info/top_level.txt
mr_nobody-1.0.1.dist-info/RECORD
