Metadata-Version: 2.4
Name: mr_nobody
Version: 1.0.1
Summary: Collection of 10 C programs
Home-page: https://github.com/yourusername/myprograms
Author: Your Name
Author-email: you@example.com
Dynamic: author
Dynamic: author-email
Dynamic: home-page
Dynamic: summary
